typedecorator
