Metadata-Version: 1.1
Name: typedecorator
Version: 0.0.3
Summary: Decorator-based type checking library for Python 2 and 3
Home-page: https://github.com/dobarkod/typedecorator/
Author: Senko Rasic
Author-email: senko.rasic@goodcode.io
License: MIT
Platform: UNKNOWN
Classifier: Intended Audience :: Developers
Classifier: License :: OSI Approved :: MIT License
Classifier: Programming Language :: Python
Classifier: Programming Language :: Python :: 3
Classifier: Topic :: Software Development :: Libraries :: Python Modules
